djangoldp_account/__init__.py
djangoldp_account/admin.py
djangoldp_account/apps.py
djangoldp_account/djangoldp_settings.py
djangoldp_account/djangoldp_urls.py
djangoldp_account/errors.py
djangoldp_account/factories.py
djangoldp_account/filters.py
djangoldp_account/forms.py
djangoldp_account/models.py
djangoldp_account/permissions.py
djangoldp_account/settings.py
djangoldp_account/views.py
djangoldp_account/auth/__init__.py
djangoldp_account/auth/backends.py
djangoldp_account/auth/middleware.py
djangoldp_account/auth/solid.py
djangoldp_account/endpoints/__init__.py
djangoldp_account/endpoints/rp_login.py
djangoldp_account/endpoints/webfinger.py
djangoldp_account/locale/de/LC_MESSAGES/django.mo
djangoldp_account/locale/de/LC_MESSAGES/django.po
djangoldp_account/locale/en/LC_MESSAGES/django.mo
djangoldp_account/locale/en/LC_MESSAGES/django.po
djangoldp_account/locale/es/LC_MESSAGES/django.mo
djangoldp_account/locale/es/LC_MESSAGES/django.po
djangoldp_account/locale/fr/LC_MESSAGES/django.mo
djangoldp_account/locale/fr/LC_MESSAGES/django.po
djangoldp_account/management/__init__.py
djangoldp_account/management/commands/__init__.py
djangoldp_account/management/commands/create_distant_admin.py
djangoldp_account/management/commands/fill_user_fields.py
djangoldp_account/management/commands/import_csv.py
djangoldp_account/management/commands/mock_account.py
djangoldp_account/migrations/0001_initial.py
djangoldp_account/migrations/0002_auto_20190917_1141.py
djangoldp_account/migrations/0003_auto_20191024_0854.py
djangoldp_account/migrations/0004_auto_20191203_0921.py
djangoldp_account/migrations/0005_ldpuser_default_redirect_uri.py
djangoldp_account/migrations/0006_auto_20200121_1321.py
djangoldp_account/migrations/0007_auto_20200130_1242.py
djangoldp_account/migrations/0008_auto_20200130_1251.py
djangoldp_account/migrations/0009_auto_20200429_1346.py
djangoldp_account/migrations/0010_auto_20200501_1207.py
djangoldp_account/migrations/0011_auto_20200501_1420.py
djangoldp_account-5.0.0.dist-info/METADATA
djangoldp_account-5.0.0.dist-info/WHEEL
djangoldp_account-5.0.0.dist-info/top_level.txt
djangoldp_account-5.0.0.dist-info/RECORD
