Metadata-Version: 2.4
Name: djangoldp_account
Version: 5.0.0
Summary: djangoldp package for account and chat data models
Home-page: http://git.happy-dev.fr/startinblox/djangoldp_account
Author: Startin'blox
Author-email: tech@startinblox.com
License: MIT
Requires-Dist: djangoldp~=5.0.0
Requires-Dist: django_registration~=3.4.0
Requires-Dist: validators~=0.20.0
Requires-Dist: oic~=1.6.0
Requires-Dist: django-webidoidc-provider~=2.0.0
Requires-Dist: djangorestframework>=3.14.0
Provides-Extra: dev
Requires-Dist: factory_boy>=2.11.0; extra == "dev"
